[
    {
        "Arr": [{
            "IntArr": [
                101,
                102
            ],
            "StrArr": [
                "啦啦啦啦",
                "嘞嘞嘞嘞"
            ],
            "Name": "第一个-A"
        }],
        "Id": 10001,
        "Name": 10001
    },
    {
        "Arr": [{
            "IntArr": [
                201,
                202
            ],
            "StrArr": [
                "biubiubiubiu",
                "唰唰唰唰"
            ],
            "Name": "测试项-A"
        }],
        "Id": 10002,
        "Name": 10002
    },
    {
        "Arr": [{
            "IntArr": [301],
            "StrArr": [],
            "Name": "测试项-C"
        }],
        "Id": 10003,
        "Name": 10003
    }
]